trackcell/__init__.py
trackcell/io/__init__.py
trackcell/io/read_data.py
trackcell/pl/__init__.py
trackcell/pl/plot.py
trackcell/tl/__init__.py
trackcell/tl/spatial.py
trackcell-0.3.10.dist-info/METADATA
trackcell-0.3.10.dist-info/WHEEL
trackcell-0.3.10.dist-info/RECORD
