Metadata-Version: 2.4
Name: trackcell
Version: 0.3.10
Summary: A Python package for processing single-cell and spatial transcriptomics data
Author: Zan Yuan
Author-email: yfinddream@gmail.com
Requires-Python: >=3.10,<4.0
Classifier: Programming Language :: Python :: 3
Classifier: Programming Language :: Python :: 3.10
Classifier: Programming Language :: Python :: 3.11
Classifier: Programming Language :: Python :: 3.12
Classifier: Programming Language :: Python :: 3.13
Classifier: Programming Language :: Python :: 3.14
Requires-Dist: geopandas (>=1.1.1,<2.0.0)
Requires-Dist: imageio (>=2.31.0,<3.0.0)
Requires-Dist: numpy (>=1.24.0,<2.0.0)
Requires-Dist: pandas (>=2.1.0,<3.0.0)
Requires-Dist: scanpy (>=1.9.0,<2.0.0)
Requires-Dist: shapely (>=2.0.0,<3.0.0)
